{
  "snapshotBlock": 25002064,
  "snapshotDate": "2026-05-01",
  "chain": "ethereum",
  "positions": [
    {
      "address": "0x44Bfc2a260f091f8365ba8b240cD9491903467b9",
      "original": "0x44Bfc2a260f091f8365ba8b240cD9491903467b9",
      "isOriginal": true,
      "collateral": "0x2E880962A9609aA3eab4DEF919FE9E917E99073B",
      "collateralName": "Boss Info AG",
      "collateralSymbol": "BOSS",
      "collateralDecimals": 0,
      "limit": "2000000000000000000000000",
      "minimumCollateral": "1000",
      "expiration": 1795537115,
      "start": 1764433115,
      "challengePeriod": 345600,
      "riskPremiumPPM": 0,
      "reserveContribution": 400000
    },
    {
      "address": "0x5F2c10f779B7f0C44ee80128A3d7ac75B255bb95",
      "original": "0x5F2c10f779B7f0C44ee80128A3d7ac75B255bb95",
      "isOriginal": true,
      "collateral": "0xcbB7C0000aB88B473b1f5aFd9ef808440eed33Bf",
      "collateralName": "Coinbase Wrapped BTC",
      "collateralSymbol": "cbBTC",
      "collateralDecimals": 8,
      "limit": "5000000000000000000000000",
      "minimumCollateral": "20000000",
      "expiration": 1866708191,
      "start": 1773396191,
      "challengePeriod": 86400,
      "riskPremiumPPM": 0,
      "reserveContribution": 200000
    },
    {
      "address": "0xC862bDC0417eC73980ee79AAE0eEFDEA68f88615",
      "original": "0xC862bDC0417eC73980ee79AAE0eEFDEA68f88615",
      "isOriginal": true,
      "collateral": "0xD533a949740bb3306d119CC777fa900bA034cd52",
      "collateralName": "Curve DAO Token",
      "collateralSymbol": "CRV",
      "collateralDecimals": 18,
      "limit": "2000000000000000000000000",
      "minimumCollateral": "20000000000000000000000",
      "expiration": 1798202411,
      "start": 1767098411,
      "challengePeriod": 43200,
      "riskPremiumPPM": 20000,
      "reserveContribution": 250000
    },
    {
      "address": "0x0C98db77782c4CB8B96479719e695b524AFEAd59",
      "original": "0x0C98db77782c4CB8B96479719e695b524AFEAd59",
      "isOriginal": true,
      "collateral": "0x6810e776880C02933D47DB1b9fc05908e5386b96",
      "collateralName": "Gnosis Token",
      "collateralSymbol": "GNO",
      "collateralDecimals": 18,
      "limit": "2000000000000000000000000",
      "minimumCollateral": "350000000000000000000",
      "expiration": 1819461203,
      "start": 1757253203,
      "challengePeriod": 172800,
      "riskPremiumPPM": 0,
      "reserveContribution": 370000
    },
    {
      "address": "0x224Bc870A661cC77742d63B6C1Fe82dF1841e0D5",
      "original": "0x224Bc870A661cC77742d63B6C1Fe82dF1841e0D5",
      "isOriginal": true,
      "collateral": "0x343324F53CBEEE3Ee6d171f2a20F005964C98047",
      "collateralName": "Switzerlend AG C1 Shares SHA",
      "collateralSymbol": "LENDS",
      "collateralDecimals": 0,
      "limit": "1000000000000000000000000",
      "minimumCollateral": "500",
      "expiration": 1801923179,
      "start": 1770819179,
      "challengePeriod": 345600,
      "riskPremiumPPM": 3000,
      "reserveContribution": 400000
    },
    {
      "address": "0xAe4bE19e25a10ce9B67d76DC2c8C774F4850B215",
      "original": "0xAe4bE19e25a10ce9B67d76DC2c8C774F4850B215",
      "isOriginal": true,
      "collateral": "0x8c1BEd5b9a0928467c9B1341Da1D7BD5e10b6549",
      "collateralName": "Liquid Staked ETH",
      "collateralSymbol": "LsETH",
      "collateralDecimals": 18,
      "limit": "5000000000000000000000000",
      "minimumCollateral": "5000000000000000000",
      "expiration": 1796560895,
      "start": 1734352895,
      "challengePeriod": 86400,
      "riskPremiumPPM": 0,
      "reserveContribution": 250000
    },
    {
      "address": "0x3484c2aaF6Cb7c27AA68c89edCDAc878020A4DA7",
      "original": "0x3484c2aaF6Cb7c27AA68c89edCDAc878020A4DA7",
      "isOriginal": true,
      "collateral": "0x45804880De22913dAFE09f4980848ECE6EcbAf78",
      "collateralName": "Paxos Gold",
      "collateralSymbol": "PAXG",
      "collateralDecimals": 18,
      "limit": "5000000000000000000000000",
      "minimumCollateral": "2000000000000000000",
      "expiration": 1861378883,
      "start": 1768066883,
      "challengePeriod": 86400,
      "riskPremiumPPM": 5000,
      "reserveContribution": 100000
    },
    {
      "address": "0x9cf4E932285474e72b82b288C4064054223bA502",
      "original": "0x9cf4E932285474e72b82b288C4064054223bA502",
      "isOriginal": true,
      "collateral": "0x553C7f9C780316FC1D34b8e14ac2465Ab22a090B",
      "collateralName": "RealUnit Shares",
      "collateralSymbol": "REALU",
      "collateralDecimals": 0,
      "limit": "2500000000000000000000000",
      "minimumCollateral": "5000",
      "expiration": 1864280171,
      "start": 1770968171,
      "challengePeriod": 129600,
      "riskPremiumPPM": 0,
      "reserveContribution": 150000
    },
    {
      "address": "0x6880881AE5a79F0C2657162A0F64072C075A60Ce",
      "original": "0x6880881AE5a79F0C2657162A0F64072C075A60Ce",
      "isOriginal": true,
      "collateral": "0xFeDC5f4a6c38211c1338aa411018DFAf26612c08",
      "collateralName": "SPDR S&P 500 ETF (Ondo Tokenized)",
      "collateralSymbol": "SPYon",
      "collateralDecimals": 18,
      "limit": "5000000000000000000000000",
      "minimumCollateral": "10000000000000000000",
      "expiration": 1865595059,
      "start": 1772283059,
      "challengePeriod": 86400,
      "riskPremiumPPM": 0,
      "reserveContribution": 100000
    },
    {
      "address": "0x8E2Dc1eD2ecF29def3a5c436455162d0639E2cf8",
      "original": "0x8E2Dc1eD2ecF29def3a5c436455162d0639E2cf8",
      "isOriginal": true,
      "collateral": "0x2260FAC5E5542a773Aa44fBCfeDf7C193bc2C599",
      "collateralName": "Wrapped BTC",
      "collateralSymbol": "WBTC",
      "collateralDecimals": 8,
      "limit": "4000000000000000000000000",
      "minimumCollateral": "10000000",
      "expiration": 1825757531,
      "start": 1763549531,
      "challengePeriod": 172800,
      "riskPremiumPPM": 5000,
      "reserveContribution": 200000
    },
    {
      "address": "0xabe499cdb61a76a8bFAa49822035DbE9a04aEDCf",
      "original": "0x49C431454C40ecbf848096f2753B2ABC3A699a10",
      "isOriginal": false,
      "collateral": "0xC02aaA39b223FE8D0A0e5C4F27eAD9083C756Cc2",
      "collateralName": "Wrapped Ether",
      "collateralSymbol": "WETH",
      "collateralDecimals": 18,
      "limit": "10000000000000000000000000",
      "minimumCollateral": "2000000000000000000",
      "expiration": 1827690503,
      "start": 1734378503,
      "challengePeriod": 86400,
      "riskPremiumPPM": 0,
      "reserveContribution": 250000
    },
    {
      "address": "0x826C54287c0C1E2A4D0fbF81E2e734c85C48d3f4",
      "original": "0x826C54287c0C1E2A4D0fbF81E2e734c85C48d3f4",
      "isOriginal": true,
      "collateral": "0x7f39C581F595B53c5cb19bD0b3f8dA6c935E2Ca0",
      "collateralName": "Wrapped liquid staked Ether 2.0",
      "collateralSymbol": "wstETH",
      "collateralDecimals": 18,
      "limit": "5000000000000000000000000",
      "minimumCollateral": "2000000000000000000",
      "expiration": 1830887747,
      "start": 1768679747,
      "challengePeriod": 86400,
      "riskPremiumPPM": 10000,
      "reserveContribution": 250000
    },
    {
      "address": "0x7ae56A1bE4979A05E58F55634E0698d18C1bED99",
      "original": "0x25BD3a5D6EE54f9Ec5536c6fF20C0685d953A70A",
      "isOriginal": false,
      "collateral": "0x68749665FF8D2d112Fa859AA293F07A622782F38",
      "collateralName": "Tether Gold",
      "collateralSymbol": "XAUt",
      "collateralDecimals": 6,
      "limit": "5000000000000000000000000",
      "minimumCollateral": "2000000",
      "expiration": 1861378979,
      "start": 1768066979,
      "challengePeriod": 86400,
      "riskPremiumPPM": 5000,
      "reserveContribution": 100000
    },
    {
      "address": "0xe8017Ad9a703BAaE37C23549B3B30841cAF3e873",
      "original": "0xe8017Ad9a703BAaE37C23549B3B30841cAF3e873",
      "isOriginal": true,
      "collateral": "0x23346B04a7f55b8760E5860AA5A77383D63491cD",
      "collateralName": "Staked yBOLD",
      "collateralSymbol": "ysyBOLD",
      "collateralDecimals": 18,
      "limit": "1000000000000000000000000",
      "minimumCollateral": "7500000000000000000000",
      "expiration": 1806070343,
      "start": 1774966343,
      "challengePeriod": 86400,
      "riskPremiumPPM": 7500,
      "reserveContribution": 200000
    }
  ]
}